topaz/__init__.py
topaz/bibtex.py
topaz/constants.py
topaz/convert.py
topaz/objects.py
topaz/protocols.conf
topaz/protocols/__init__.py
topaz/protocols/protocol_base.py
topaz/protocols/protocol_topaz_import.py
topaz/protocols/protocol_topaz_picking.py
topaz/protocols/protocol_topaz_training.py
topaz/tests/__init__.py
topaz/tests/test_protocol_topaz.py
scipion_em_topaz-3.1.0.dist-info/LICENSE
scipion_em_topaz-3.1.0.dist-info/METADATA
scipion_em_topaz-3.1.0.dist-info/WHEEL
scipion_em_topaz-3.1.0.dist-info/entry_points.txt
scipion_em_topaz-3.1.0.dist-info/top_level.txt
scipion_em_topaz-3.1.0.dist-info/RECORD
