Metadata-Version: 2.1
Name: scipion-em-topaz
Version: 3.1.0
Summary: Plugin to use Topaz within the Scipion framework
Author-email: Scipion Madrid <scipion@cnb.csic.es>
License: GNU General Public License v3 (GPLv3)
Project-URL: Homepage, https://github.com/scipion-em/scipion-em-topaz
Project-URL: Repository, https://github.com/scipion-em/scipion-em-topaz
Project-URL: Issues, https://github.com/scipion-em/scipion-em-topaz/issues
Keywords: scipion,electron-microscopy,cryo-em,structural-biology,image-processing,scipion-3.0
Requires-Python: >=3.8
License-File: LICENSE
Requires-Dist: scipion-em
